cdk_cloudformation_netapp_fsxn_cifsshare/__init__.py
cdk_cloudformation_netapp_fsxn_cifsshare/py.typed
cdk_cloudformation_netapp_fsxn_cifsshare/_jsii/__init__.py
cdk_cloudformation_netapp_fsxn_cifsshare/_jsii/netapp-fsxn-cifsshare@1.0.0-alpha.7.jsii.tgz
cdk_cloudformation_netapp_fsxn_cifsshare-1.0.0a7.dist-info/LICENSE
cdk_cloudformation_netapp_fsxn_cifsshare-1.0.0a7.dist-info/METADATA
cdk_cloudformation_netapp_fsxn_cifsshare-1.0.0a7.dist-info/WHEEL
cdk_cloudformation_netapp_fsxn_cifsshare-1.0.0a7.dist-info/top_level.txt
cdk_cloudformation_netapp_fsxn_cifsshare-1.0.0a7.dist-info/RECORD
