Metadata-Version: 2.2
Name: cdk-cloudformation-netapp-fsxn-cifsshare
Version: 1.0.0a7
Summary: A CIFS share is a shared folder tied to an FSx for ONTAP volume. It allows Windows and other SMB-compatible clients to access files on the volume over the network. CIFS shares can be managed with access controls and permissions to ensure secure and efficient file sharing across users and applications. Once activated, you will need a preview key to consume this resource. Please reach out to Ng-fsx-cloudformation@netapp.com to get the key. To use this resource, you would need to first cre
Home-page: https://github.com/NetApp/NetApp-CloudFormation-FSx-ONTAP-provider
Author: Amazon Web Services
License: Apache-2.0
Project-URL: Source, https://github.com/cdklabs/cdk-cloudformation.git
Classifier: Intended Audience :: Developers
Classifier: Operating System :: OS Independent
Classifier: Programming Language :: JavaScript
Classifier: Programming Language :: Python :: 3 :: Only
Classifier: Programming Language :: Python :: 3.8
Classifier: Programming Language :: Python :: 3.9
Classifier: Programming Language :: Python :: 3.10
Classifier: Programming Language :: Python :: 3.11
Classifier: Typing :: Typed
Classifier: License :: OSI Approved
Requires-Python: ~=3.8
License-File: LICENSE
Requires-Dist: aws-cdk-lib<3.0.0,>=2.177.0
Requires-Dist: constructs<11.0.0,>=10.4.2
Requires-Dist: jsii<2.0.0,>=1.106.0
Requires-Dist: publication>=0.0.3
Requires-Dist: typeguard<4.3.0,>=2.13.3
Dynamic: author
Dynamic: classifier
Dynamic: description
Dynamic: description-content-type
Dynamic: home-page
Dynamic: license
Dynamic: project-url
Dynamic: requires-dist
Dynamic: requires-python
Dynamic: summary
